Computer_Engineering_Laboratory/report4/systemverilog-example/sillyfunction.sv
module sillyfunction(input  logic a, b, c,
                     output logic y);

  assign y = ~a & ~b & ~c |
              a & ~b & ~c |
              a & ~b &  c;
endmodule

Computer_Engineering_Laboratory/report4/systemverilog-example/testbench_example1_vcd.sv
module testbench1();
  logic  a, b, c, y;

  // instantiate device under test
  sillyfunction dut(a, b, c, y);

  // apply inputs one at a time
  initial begin
    a = 0; b = 0; c = 0; #10;
    c = 1;               #10;
    b = 1; c = 0;        #10;
    c = 1;               #10;
    a = 1; b = 0; c = 0; #10;
    c = 1;               #10;
    b = 1; c = 0;        #10;
    c = 1;               #10;
  end

  initial begin
     $dumpfile("dump.vcd");
     $dumpvars(0,testbench1);
  end
endmodule

Computer_Engineering_Laboratory/report4/systemverilog-example/dump.vcd
$date
	Thu Dec 01 15:14:09 2016
$end
$version
	ModelSim Version 10.1d
$end
$timescale
	1ps
$end
$scope module testbench1 $end
$var reg 1 ! a $end
$var reg 1 " b $end
$var reg 1 # c $end
$var reg 1 $ y $end
$scope module dut $end
$var wire 1 % a $end
$var wire 1 & b $end
$var wire 1 ' c $end
$var reg 1 ( y $end
$upscope $end
$upscope $end
$enddefinitions $end
#0
$dumpvars
0!
0"
0#
1$
1(
0%
0&
0'
$end
#10
1#
1'
0(
0$
#20
1"
0#
1&
0'
#30
1#
1'
#40
1!
0"
0#
1%
0&
0'
1(
1$
#50
1#
1'
#60
1"
0#
1&
0'
0(
0$
#70
1#
1'
